Workbook

Sheet Dashboard
A1: Fractional CFO Toolkit
A2: 3-Year Financial Model | Unit Economics | Expense Audit
A4: Key Metrics
A6: Year 1 Revenue | B6: ='Income Statement'!N13 -> 393041.93
A7: Year 3 Revenue | B7: ='Income Statement'!P13 -> 643256.05
A8: Year 1 Net Income | B8: ='Income Statement'!N32 -> -103752.49
A9: Year 3 Net Income | B9: ='Income Statement'!P32 -> 95422.788
A10: Year 3 EBITDA Margin | B10: ='Income Statement'!P26/'Income Statement'!P13 -> 0.22477572
A11: LTV : CAC | B11: ='Unit Economics'!B21 -> 13.75
A12: Year 1 Ending Cash | B12: =Cash!C22 -> -26260.371
A13: Audit Savings Found | B13: ='Leakage Audit'!K5 -> 30729.6
A16: What This Model Shows
A17: • Revenue scales over the 3-year horizon as the customer base grows | D17: `
A18: • Business trajectory reveals operating leverage as fixed costs are spread across more revenue
A19: • Monthly build surfaces the Year 1 cash low point and any funding need
A20: • Automated expense audit flags recurring waste and quantifies recoverable savings
A21: • Unit economics (LTV:CAC, payback) gauge customer acquisition efficiency
A35: Revenue & Net Income by Year ($)
B36: Year 1 | C36: Year 2 | D36: Year 3
A37: Revenue | B37: ='Income Statement'!N13 -> 393041.93 | C37: ='Income Statement'!O13 -> 531163.1 | D37: ='Income Statement'!P13 -> 643256.05
A38: Net Income | B38: ='Income Statement'!N32 -> -103752.49 | C38: ='Income Statement'!O32 -> 15133.207 | D38: ='Income Statement'!P32 -> 95422.788
A41: Color Key — Cell Types
A42: Hard-coded inputs
A43: Formulas / calculations
A44: Links to other worksheets
A45: Links to other files
A46: Links to data providers (CIQ, FactSet)

Sheet Assumptions
A1: Assumptions - Iron & Oak Fitness Studio
A3: Revenue Drivers
A4: Starting Members | B4: 300
A5: Monthly New Members | B5: 25
A6: Monthly Churn Rate | B6: 0.04
A7: Avg Monthly Membership Fee | B7: 89
A8: Annual Price Increase | B8: 0.05
A10: Cost Drivers
A11: Rent(Monthly) | B11: 8500
A12: Staff Wages (Monthly) | B12: 18000
A13: Equipment Lease (Monthly) | B13: 2200
A14: Marketing (Monthly) | B14: 3500
A15: Other OpEx (Monthly) | B15: 2800
A16: Variable Cost per Member | B16: 12
A18: Working Capital & Financing
A19: Days Receivable (DSO) | B19: 5
A20: Days Payable (DPO) | B20: 30
A21: Starting Cash | B21: 40000
A22: Starting Debt | B22: 60000
A23: Interest Rate on Debt | B23: 0.08
A24: Tax Rate | B24: 0.21
A26: Capital & Depreciation
A27: Starting PP&E (net) | B27: 95000
A28: Annual Capex | B28: 15000
A29: Depreciation | B29: 19000
A32: Color Key — Cell Types
A33: Hard-coded inputs
A34: Formulas / calculations
A35: Links to other worksheets
A36: Links to other files
A37: Links to data providers (CIQ, FactSet)

Sheet Income Statement
B2: Month | N2: Annual
B3: 1 | C3: 2 | D3: 3 | E3: 4 | F3: 5 | G3: 6 | H3: 7 | I3: 8 | J3: 9 | K3: 10 | L3: 11 | M3: 12 | N3: Year 1 | O3: Year 2 | P3: Year 3
A5: Member Waterfall
A6: Beginning Members | B6: =Assumptions!B4 -> 300 | C6: =B9 -> 313 | D6: =C9 -> 325.48 | E6: =D9 -> 337.4608 | F6: =E9 -> 348.96237 | G6: =F9 -> 360.00387 | H6: =G9 -> 370.60372 | I6: =H9 -> 380.77957 | J6: =I9 -> 390.54839 | ... M6: =L9 -> 417.57222 | N6: =B6 -> 300 | O6: =N9 -> 425.86933 | P6: =O9 -> 521.45205
A7: New Members | B7: =Assumptions!$B$5 -> 25 | C7: =Assumptions!$B$5 -> 25 | D7: =Assumptions!$B$5 -> 25 | E7: =Assumptions!$B$5 -> 25 | F7: =Assumptions!$B$5 -> 25 | G7: =Assumptions!$B$5 -> 25 | H7: =Assumptions!$B$5 -> 25 | I7: =Assumptions!$B$5 -> 25 | ... M7: =Assumptions!$B$5 -> 25 | N7: =SUM(B7:M7) -> 300 | O7: =Assumptions!$B$5*12 -> 300 | P7: =Assumptions!$B$5*12 -> 300
A8: Churned Members | B8: =B6*Assumptions!$B$6 -> 12 | C8: =C6*Assumptions!$B$6 -> 12.52 | D8: =D6*Assumptions!$B$6 -> 13.0192 | E8: =E6*Assumptions!$B$6 -> 13.498432 | F8: =F6*Assumptions!$B$6 -> 13.958495 | G8: =G6*Assumptions!$B$6 -> 14.400155 | H8: =H6*Assumptions!$B$6 -> 14.824149 | I8: =I6*Assumptions!$B$6 -> 15.231183 | ... M8: =M6*Assumptions!$B$6 -> 16.702889 | N8: =SUM(B8:M8) -> 174.13067 | O8: =O6*Assumptions!$B$6*12 -> 204.41728 | P8: =P6*Assumptions!$B$6*12 -> 250.29698 | R8: Multiplying Churn x 12 is a simplication
A9: Ending Members | B9: =B6+B7-B8 -> 313 | C9: =C6+C7-C8 -> 325.48 | D9: =D6+D7-D8 -> 337.4608 | E9: =E6+E7-E8 -> 348.96237 | F9: =F6+F7-F8 -> 360.00387 | G9: =G6+G7-G8 -> 370.60372 | H9: =H6+H7-H8 -> 380.77957 | I9: =I6+I7-I8 -> 390.54839 | ... M9: =M6+M7-M8 -> 425.86933 | N9: =M9 -> 425.86933 | O9: =O6+O7-O8 -> 521.45205 | P9: =P6+P7-P8 -> 571.15507
A10: Average Members | B10: =(B6+B9)/2 -> 306.5 | C10: =(C6+C9)/2 -> 319.24 | D10: =(D6+D9)/2 -> 331.4704 | E10: =(E6+E9)/2 -> 343.21158 | F10: =(F6+F9)/2 -> 354.48312 | G10: =(G6+G9)/2 -> 365.3038 | H10: =(H6+H9)/2 -> 375.69164 | I10: =(I6+I9)/2 -> 385.66398 | ... P10: =(P6+P9)/2 -> 546.30356
A12: Income Statement
A13: Membership Revenue | B13: =B10*Assumptions!$B$7 -> 27278.5 | C13: =C10*Assumptions!$B$7 -> 28412.36 | D13: =D10*Assumptions!$B$7 -> 29500.866 | E13: =E10*Assumptions!$B$7 -> 30545.831 | F13: =F10*Assumptions!$B$7 -> 31548.998 | G13: =G10*Assumptions!$B$7 -> 32512.038 | H13: =H10*Assumptions!$B$7 -> 33436.556 | I13: =I10*Assumptions!$B$7 -> 34324.094 | ... M13: =M10*Assumptions!$B$7 -> 37533.149 | N13: =SUM(B13:M13) -> 393041.93 | O13: =O10*Assumptions!$B$7*(1+Assumptions!$B$8)*12 -> 531163.1 | P13: =P10*Assumptions!$B$7*(1+Assumptions!$B$8)^2*12 -> 643256.05
A14: Variable Costs | B14: =B10*Assumptions!$B$16 -> 3678 | C14: =C10*Assumptions!$B$16 -> 3830.88 | D14: =D10*Assumptions!$B$16 -> 3977.6448 | E14: =E10*Assumptions!$B$16 -> 4118.539 | F14: =F10*Assumptions!$B$16 -> 4253.7974 | G14: =G10*Assumptions!$B$16 -> 4383.6455 | H14: =H10*Assumptions!$B$16 -> 4508.2997 | I14: =I10*Assumptions!$B$16 -> 4627.9677 | ... M14: =M10*Assumptions!$B$16 -> 5060.6493 | N14: =SUM(B14:M14) -> 52994.417 | O14: =O10*Assumptions!$B$16*12 -> 68207.139 | P14: =P10*Assumptions!$B$16*12 -> 78667.712
A15: Gross Profit | B15: =B13-B14 -> 23600.5 | C15: =C13-C14 -> 24581.48 | D15: =D13-D14 -> 25523.221 | E15: =E13-E14 -> 26427.292 | F15: =F13-F14 -> 27295.2 | G15: =G13-G14 -> 28128.392 | H15: =H13-H14 -> 28928.257 | I15: =I13-I14 -> 29696.126 | ... P15: =P13-P14 -> 564588.34
A16: Gross Margin % | B16: =B15/B13 -> 0.86516854 | C16: =C15/C13 -> 0.86516854 | D16: =D15/D13 -> 0.86516854 | E16: =E15/E13 -> 0.86516854 | F16: =F15/F13 -> 0.86516854 | G16: =G15/G13 -> 0.86516854 | H16: =H15/H13 -> 0.86516854 | I16: =I15/I13 -> 0.86516854 | ... P16: =P15/P13 -> 0.87770389
A18: Operating Expenses
A19: Rent | B19: =Assumptions!$B$11 -> 8500 | C19: =Assumptions!$B$11 -> 8500 | D19: =Assumptions!$B$11 -> 8500 | E19: =Assumptions!$B$11 -> 8500 | F19: =Assumptions!$B$11 -> 8500 | G19: =Assumptions!$B$11 -> 8500 | H19: =Assumptions!$B$11 -> 8500 | I19: =Assumptions!$B$11 -> 8500 | ... M19: =Assumptions!$B$11 -> 8500 | N19: =SUM(B19:M19) -> 102000 | O19: =Assumptions!$B$11*12 -> 102000 | P19: =Assumptions!$B$11*12 -> 102000
A20: Staff Wages | B20: =Assumptions!$B$12 -> 18000 | C20: =Assumptions!$B$12 -> 18000 | D20: =Assumptions!$B$12 -> 18000 | E20: =Assumptions!$B$12 -> 18000 | F20: =Assumptions!$B$12 -> 18000 | G20: =Assumptions!$B$12 -> 18000 | H20: =Assumptions!$B$12 -> 18000 | I20: =Assumptions!$B$12 -> 18000 | ... M20: =Assumptions!$B$12 -> 18000 | N20: =SUM(B20:M20) -> 216000 | O20: =Assumptions!$B$12*12 -> 216000 | P20: =Assumptions!$B$12*12 -> 216000
A21: Equipment Lease | B21: =Assumptions!$B$13 -> 2200 | C21: =Assumptions!$B$13 -> 2200 | D21: =Assumptions!$B$13 -> 2200 | E21: =Assumptions!$B$13 -> 2200 | F21: =Assumptions!$B$13 -> 2200 | G21: =Assumptions!$B$13 -> 2200 | H21: =Assumptions!$B$13 -> 2200 | I21: =Assumptions!$B$13 -> 2200 | ... M21: =Assumptions!$B$13 -> 2200 | N21: =SUM(B21:M21) -> 26400 | O21: =Assumptions!$B$13*12 -> 26400 | P21: =Assumptions!$B$13*12 -> 26400
A22: Marketing | B22: =Assumptions!$B$14 -> 3500 | C22: =Assumptions!$B$14 -> 3500 | D22: =Assumptions!$B$14 -> 3500 | E22: =Assumptions!$B$14 -> 3500 | F22: =Assumptions!$B$14 -> 3500 | G22: =Assumptions!$B$14 -> 3500 | H22: =Assumptions!$B$14 -> 3500 | I22: =Assumptions!$B$14 -> 3500 | ... M22: =Assumptions!$B$14 -> 3500 | N22: =SUM(B22:M22) -> 42000 | O22: =Assumptions!$B$14*12 -> 42000 | P22: =Assumptions!$B$14*12 -> 42000
A23: Other Opex | B23: =Assumptions!$B$15 -> 2800 | C23: =Assumptions!$B$15 -> 2800 | D23: =Assumptions!$B$15 -> 2800 | E23: =Assumptions!$B$15 -> 2800 | F23: =Assumptions!$B$15 -> 2800 | G23: =Assumptions!$B$15 -> 2800 | H23: =Assumptions!$B$15 -> 2800 | I23: =Assumptions!$B$15 -> 2800 | ... M23: =Assumptions!$B$15 -> 2800 | N23: =SUM(B23:M23) -> 33600 | O23: =Assumptions!$B$15*12 -> 33600 | P23: =Assumptions!$B$15*12 -> 33600
A24: Total Opex | B24: =SUM(B19:B23) -> 35000 | C24: =SUM(C19:C23) -> 35000 | D24: =SUM(D19:D23) -> 35000 | E24: =SUM(E19:E23) -> 35000 | F24: =SUM(F19:F23) -> 35000 | G24: =SUM(G19:G23) -> 35000 | H24: =SUM(H19:H23) -> 35000 | I24: =SUM(I19:I23) -> 35000 | ... P24: =SUM(P19:P23) -> 420000
A26: EBITDA | B26: =B15-B24 -> -11399.5 | C26: =C15-C24 -> -10418.52 | D26: =D15-D24 -> -9476.7792 | E26: =E15-E24 -> -8572.708 | F26: =F15-F24 -> -7704.7997 | G26: =G15-G24 -> -6871.6077 | H26: =H15-H24 -> -6071.7434 | I26: =I15-I24 -> -5303.8737 | ... P26: =P15-P24 -> 144588.34
A27: Depreciation | B27: =Assumptions!$B$29/12 -> 1583.3333 | C27: =Assumptions!$B$29/12 -> 1583.3333 | D27: =Assumptions!$B$29/12 -> 1583.3333 | E27: =Assumptions!$B$29/12 -> 1583.3333 | F27: =Assumptions!$B$29/12 -> 1583.3333 | G27: =Assumptions!$B$29/12 -> 1583.3333 | H27: =Assumptions!$B$29/12 -> 1583.3333 | I27: =Assumptions!$B$29/12 -> 1583.3333 | ... M27: =Assumptions!$B$29/12 -> 1583.3333 | N27: =Assumptions!$B$29 -> 19000 | O27: =Assumptions!$B$29 -> 19000 | P27: =Assumptions!$B$29 -> 19000
A28: EBIT | B28: =B26-B27 -> -12982.833 | C28: =C26-C27 -> -12001.853 | D28: =D26-D27 -> -11060.113 | E28: =E26-E27 -> -10156.041 | F28: =F26-F27 -> -9288.133 | G28: =G26-G27 -> -8454.9411 | H28: =H26-H27 -> -7655.0767 | I28: =I26-I27 -> -6887.207 | ... P28: =P26-P27 -> 125588.34
A29: Interest Expense | B29: =Assumptions!$B$22*Assumptions!$B$23/12 -> 400 | C29: =Assumptions!$B$22*Assumptions!$B$23/12 -> 400 | D29: =Assumptions!$B$22*Assumptions!$B$23/12 -> 400 | E29: =Assumptions!$B$22*Assumptions!$B$23/12 -> 400 | F29: =Assumptions!$B$22*Assumptions!$B$23/12 -> 400 | G29: =Assumptions!$B$22*Assumptions!$B$23/12 -> 400 | H29: =Assumptions!$B$22*Assumptions!$B$23/12 -> 400 | I29: =Assumptions!$B$22*Assumptions!$B$23/12 -> 400 | ... M29: =Assumptions!$B$22*Assumptions!$B$23/12 -> 400 | N29: =Assumptions!$B$22*Assumptions!$B$23 -> 4800 | O29: =Assumptions!$B$22*Assumptions!$B$23 -> 4800 | P29: =Assumptions!$B$22*Assumptions!$B$23 -> 4800 | R29: Assumes debt stays flat at starting balance (SMB)
A30: Pre-Tax Income | B30: =B28-B29 -> -13382.833 | C30: =C28-C29 -> -12401.853 | D30: =D28-D29 -> -11460.113 | E30: =E28-E29 -> -10556.041 | F30: =F28-F29 -> -9688.133 | G30: =G28-G29 -> -8854.9411 | H30: =H28-H29 -> -8055.0767 | I30: =I28-I29 -> -7287.207 | ... P30: =P28-P29 -> 120788.34
A31: Taxes | B31: =MAX(B30,0)*Assumptions!$B$24 -> 0 | C31: =MAX(C30,0)*Assumptions!$B$24 -> 0 | D31: =MAX(D30,0)*Assumptions!$B$24 -> 0 | E31: =MAX(E30,0)*Assumptions!$B$24 -> 0 | F31: =MAX(F30,0)*Assumptions!$B$24 -> 0 | G31: =MAX(G30,0)*Assumptions!$B$24 -> 0 | H31: =MAX(H30,0)*Assumptions!$B$24 -> 0 | I31: =MAX(I30,0)*Assumptions!$B$24 -> 0 | ... P31: =MAX(P30,0)*Assumptions!$B$24 -> 25365.551
A32: Net Income | B32: =B30-B31 -> -13382.833 | C32: =C30-C31 -> -12401.853 | D32: =D30-D31 -> -11460.113 | E32: =E30-E31 -> -10556.041 | F32: =F30-F31 -> -9688.133 | G32: =G30-G31 -> -8854.9411 | H32: =H30-H31 -> -8055.0767 | I32: =I30-I31 -> -7287.207 | ... P32: =P30-P31 -> 95422.788
A34: Net Margin % | B34: =B32/B13 -> -0.49060005 | C34: =C32/C13 -> -0.43649501 | D34: =D32/D13 -> -0.38846699 | E34: =E32/E13 -> -0.34558043 | F34: =F32/F13 -> -0.30708212 | G34: =G32/G13 -> -0.27235884 | H34: =H32/H13 -> -0.24090629 | I34: =I32/I13 -> -0.21230588 | ... P34: =P32/P13 -> 0.1483434
A37: Color Key — Cell Types
A38: Hard-coded inputs
A39: Formulas / calculations
A40: Links to other worksheets
A41: Links to other files
A42: Links to data providers (CIQ, FactSet)

Sheet Balance Sheet
B3: Year 0 | C3: Year 1 | D3: Year 2 | E3: Year 3
A5: Assets
A6: Cash | B6: =Assumptions!$B$21 -> 40000 | C6: =Cash!C22 -> -26260.371 | D6: =Cash!D22 -> -7768.8744 | E6: =Cash!E22 -> 90978.166
A7: Accounts Receivable | B7: 0 | C7: ='Income Statement'!N13/365*Assumptions!$B$19 -> 5384.136 | D7: ='Income Statement'!O13/365*Assumptions!$B$19 -> 7276.2068 | E7: ='Income Statement'!P13/365*Assumptions!$B$19 -> 8811.7267
A8: PP&E (net) | B8: =Assumptions!$B$27 -> 95000 | C8: =B8+Assumptions!$B$28-Assumptions!$B$29 -> 91000 | D8: =C8+Assumptions!$B$28-Assumptions!$B$29 -> 87000 | E8: =D8+Assumptions!$B$28-Assumptions!$B$29 -> 83000
A9: Total Assets | B9: =B6+B7+B8 -> 135000 | C9: =C6+C7+C8 -> 70123.765 | D9: =D6+D7+D8 -> 86507.332 | E9: =E6+E7+E8 -> 182789.89
A11: Liabilities
A12: Accounts Payable | B12: 0 | C12: =('Income Statement'!N14+'Income Statement'!N24)/365*Assumptions!$B$20 -> 38876.253 | D12: =('Income Statement'!O14+'Income Statement'!O24)/365*Assumptions!$B$20 -> 40126.614 | E12: =('Income Statement'!P14+'Income Statement'!P24)/365*Assumptions!$B$20 -> 40986.387
A13: Debt | B13: =Assumptions!$B$22 -> 60000 | C13: =Assumptions!$B$22 -> 60000 | D13: =Assumptions!$B$22 -> 60000 | E13: =Assumptions!$B$22 -> 60000
A14: Total Liabilities | B14: =B12+B13 -> 60000 | C14: =C12+C13 -> 98876.253 | D14: =D12+D13 -> 100126.61 | E14: =E12+E13 -> 100986.39
A16: Equity
A17: Contributed Capital | B17: =B9-B14-B18 -> 75000 | C17: =B17 -> 75000 | D17: =C17 -> 75000 | E17: =D17 -> 75000
A18: Retained Earnings | B18: 0 | C18: =B18+'Income Statement'!N32 -> -103752.49 | D18: =C18+'Income Statement'!O32 -> -88619.282 | E18: =D18+'Income Statement'!P32 -> 6803.5059
A19: Total equity | B19: =B17+B18 -> 75000 | C19: =C17 + C18 -> -28752.489 | D19: =D17 + D18 -> -13619.282 | E19: =E17 + E18 -> 81803.506
A21: Total Liabilities + Equity | B21: =B14+B19 -> 135000 | C21: =C14+C19 -> 70123.765 | D21: =D14+D19 -> 86507.332 | E21: =E14+E19 -> 182789.89
A23: Check (Assets - L&E) | B23: =ROUND(B9-B21,2) -> 0 | C23: =ROUND(C9-C21,2) -> 0 | D23: =ROUND(D9-D21,2) -> 0 | E23: =ROUND(E9-E21,2) -> 0
A26: Color Key — Cell Types
A27: Hard-coded inputs
A28: Formulas / calculations
A29: Links to other worksheets
A30: Links to other files
A31: Links to data providers (CIQ, FactSet)

Sheet Cash
B3: Year 0 | C3: Year 1 | D3: Year 2 | E3: Year 3
A5: Operating Activities
A6: Net Income | C6: ='Income Statement'!N32 -> -103752.49 | D6: ='Income Statement'!O32 -> 15133.207 | E6: ='Income Statement'!P32 -> 95422.788
A7: (+) Depreciation | C7: ='Income Statement'!N27 -> 19000 | D7: ='Income Statement'!O27 -> 19000 | E7: ='Income Statement'!P27 -> 19000
A8: (-) Increase in AR | C8: =-('Balance Sheet'!C7-'Balance Sheet'!B7) -> -5384.136 | D8: =-('Balance Sheet'!D7-'Balance Sheet'!C7) -> -1892.0708 | E8: =-('Balance Sheet'!E7-'Balance Sheet'!D7) -> -1535.5199
A9: (+) Increase in AP | C9: ='Balance Sheet'!C12-'Balance Sheet'!B12 -> 38876.253 | D9: ='Balance Sheet'!D12-'Balance Sheet'!C12 -> 1250.3607 | E9: ='Balance Sheet'!E12-'Balance Sheet'!D12 -> 859.77313
A10: Cash from Operations | C10: =SUM(C6:C9) -> -51260.371 | D10: =SUM(D6:D9) -> 33491.497 | E10: =SUM(E6:E9) -> 113747.04
A12: Investing Activities
A13: (-) Capex | C13: =-Assumptions!$B$28 -> -15000 | D13: =-Assumptions!$B$28 -> -15000 | E13: =-Assumptions!$B$28 -> -15000
A14: Cash from Investing | C14: =C13 -> -15000 | D14: =D13 -> -15000 | E14: =E13 -> -15000
A16: Financing Activities
A17: Change in Debt | C17: ='Balance Sheet'!C13-'Balance Sheet'!B13 -> 0 | D17: ='Balance Sheet'!D13-'Balance Sheet'!C13 -> 0 | E17: ='Balance Sheet'!E13-'Balance Sheet'!D13 -> 0
A18: Cash from Financing | C18: =C17 -> 0 | D18: =D17 -> 0 | E18: =E17 -> 0
A20: Net Change in Cash | C20: =C10+C14+C18 -> -66260.371 | D20: =D10+D14+D18 -> 18491.497 | E20: =E10+E14+E18 -> 98747.041
A21: Beginning Cash | C21: =Assumptions!$B$21 -> 40000 | D21: =C22 -> -26260.371 | E21: =D22 -> -7768.8744
A22: Ending Cash | C22: =C21+C20 -> -26260.371 | D22: =D21+D20 -> -7768.8744 | E22: =E21+E20 -> 90978.166
A25: Color Key — Cell Types
A26: Hard-coded inputs
A27: Formulas / calculations
A28: Links to other worksheets
A29: Links to other files
A30: Links to data providers (CIQ, FactSet)

Sheet Unit Economics
A1: Unit Economics
A3: Revenue Per Member
A4: Avg Monthly Fee | B4: =Assumptions!$B$7 -> 89
A5: Avg Member Lifespan (months) | B5: =1/Assumptions!$B$6 -> 25
A6: Lifetime Rev per Member | B6: =B4*B5 -> 2225
A8: Cost Per Member
A9: Variable Cost / Member / Month | B9: =Assumptions!$B$16 -> 12
A10: Lifetime Variable Cost | B10: =B9*B5 -> 300
A11: Gross Profit per Member | B11: =B6-B10 -> 1925
A12: Gross Margin per Member % | B12: =B11/B6 -> 0.86516854
A14: Acquisition
A15: Monthly Marketing Spend | B15: =Assumptions!$B$14 -> 3500
A16: Monthly New members | B16: =Assumptions!$B$5 -> 25
A17: CAC (Cost to Acquire) | B17: =B15/B16 -> 140
A19: Key Ratios
A20: LTV (Lifetime Value) | B20: =B11 -> 1925
A21: LTV : CAC Ratio | B21: =B20 / B17 -> 13.75
A22: CAC Payback (Months) | B22: =B17 / (B4-B9) -> 1.8181818
A25: Color Key — Cell Types
A26: Hard-coded inputs
A27: Formulas / calculations
A28: Links to other worksheets
A29: Links to other files
A30: Links to data providers (CIQ, FactSet)

Sheet Leakage Audit
A1: Date | B1: Vendor | C1: Category | D1: Amount | E1: Recurring | F1: Months Active | G1: Flag | H1: Annualized Cost | J1: Leakage Summary
A2: 46037 | B2: ClassPass Software | C2: Software | D2: 299 | E2: Yes | F2: 12 | G2: =IF(C2="","",IF(COUNTIF(B:B,B2)>1,"Duplicate Vendor",IF(AND(E2="Yes",D2>500),"High Recurring Cost",IF(D2>AVERAGE(D:D)*2.5,"Spending Spike","")))) -> Duplicate Vendor | H2: =IF(C2="","",IF(E2="Yes",D2*F2,D2)) -> 3588 | J2: Total Flagged Items | K2: =COUNTIF(G2:G17,"Duplicate Vendor")+COUNTIF(G2:G17,"High Recurring Cost")+COUNTIF(G2:G17,"Spending Spike") -> 6
A3: 46037 | B3: MindBody Booking | C3: Software | D3: 279 | E3: Yes | F3: 12 | G3: =IF(C3="","",IF(COUNTIF(B:B,B3)>1,"Duplicate Vendor",IF(AND(E3="Yes",D3>500),"High Recurring Cost",IF(D3>AVERAGE(D:D)*2.5,"Spending Spike","")))) | H3: =IF(C3="","",IF(E3="Yes",D3*F3,D3)) -> 3348 | J3: Total Annualized Spend | K3: =SUM(H2:H17) -> 79126
A4: 46038 | B4: Spotify Business | C4: Software | D4: 27 | E4: Yes | F4: 12 | G4: =IF(C4="","",IF(COUNTIF(B:B,B4)>1,"Duplicate Vendor",IF(AND(E4="Yes",D4>500),"High Recurring Cost",IF(D4>AVERAGE(D:D)*2.5,"Spending Spike","")))) | H4: =IF(C4="","",IF(E4="Yes",D4*F4,D4)) -> 324 | J4: Flagged Annualized Cost | K4: =SUMIF(G2:G17,"Duplicate Vendor",H2:H17)+SUMIF(G2:G17,"High Recurring Cost",H2:H17)+SUMIF(G2:G17,"Spending Spike",H2:H17) -> 51216
A5: 46040 | B5: City Water | C5: Utilities | D5: 140 | E5: Yes | F5: 12 | G5: =IF(C5="","",IF(COUNTIF(B:B,B5)>1,"Duplicate Vendor",IF(AND(E5="Yes",D5>500),"High Recurring Cost",IF(D5>AVERAGE(D:D)*2.5,"Spending Spike","")))) | H5: =IF(C5="","",IF(E5="Yes",D5*F5,D5)) -> 1680 | J5: Potential Annualized Savings | K5: =K4*0.6 -> 30729.6
A6: 46042 | B6: Equipment Repair | C6: Maintenance | D6: 850 | E6: No | F6: 1 | G6: =IF(C6="","",IF(COUNTIF(B:B,B6)>1,"Duplicate Vendor",IF(AND(E6="Yes",D6>500),"High Recurring Cost",IF(D6>AVERAGE(D:D)*2.5,"Spending Spike","")))) | H6: =IF(C6="","",IF(E6="Yes",D6*F6,D6)) -> 850 | J6: Leakage % of Spend | K6: =K4/K3 -> 0.64727144
A7: 46044 | B7: Instagram Ads | C7: Marketing | D7: 400 | E7: Yes | F7: 12 | G7: =IF(C7="","",IF(COUNTIF(B:B,B7)>1,"Duplicate Vendor",IF(AND(E7="Yes",D7>500),"High Recurring Cost",IF(D7>AVERAGE(D:D)*2.5,"Spending Spike","")))) | H7: =IF(C7="","",IF(E7="Yes",D7*F7,D7)) -> 4800
A8: 46047 | B8: Google Ads | C8: Marketing | D8: 350 | E8: Yes | F8: 12 | G8: =IF(C8="","",IF(COUNTIF(B:B,B8)>1,"Duplicate Vendor",IF(AND(E8="Yes",D8>500),"High Recurring Cost",IF(D8>AVERAGE(D:D)*2.5,"Spending Spike","")))) | H8: =IF(C8="","",IF(E8="Yes",D8*F8,D8)) -> 4200
A9: 46050 | B9: Towel Service | C9: Supplies | D9: 180 | E9: Yes | F9: 12 | G9: =IF(C9="","",IF(COUNTIF(B:B,B9)>1,"Duplicate Vendor",IF(AND(E9="Yes",D9>500),"High Recurring Cost",IF(D9>AVERAGE(D:D)*2.5,"Spending Spike","")))) | H9: =IF(C9="","",IF(E9="Yes",D9*F9,D9)) -> 2160 | J9: Color Key — Cell Types
A10: 46054 | B10: Annual Insurance | C10: Insurance | D10: 4200 | E10: No | F10: 1 | G10: =IF(C10="","",IF(COUNTIF(B:B,B10)>1,"Duplicate Vendor",IF(AND(E10="Yes",D10>500),"High Recurring Cost",IF(D10>AVERAGE(D:D)*2.5,"Spending Spike","")))) -> Spending Spike | H10: =IF(C10="","",IF(E10="Yes",D10*F10,D10)) -> 4200 | J10: Hard-coded inputs
A11: 46056 | B11: Cleaning Crew | C11: Maintenance | D11: 600 | E11: Yes | F11: 12 | G11: =IF(C11="","",IF(COUNTIF(B:B,B11)>1,"Duplicate Vendor",IF(AND(E11="Yes",D11>500),"High Recurring Cost",IF(D11>AVERAGE(D:D)*2.5,"Spending Spike","")))) -> High Recurring Cost | H11: =IF(C11="","",IF(E11="Yes",D11*F11,D11)) -> 7200 | J11: Formulas / calculations
A12: 46058 | B12: Gym Software Pro | C12: Software | D12: 189 | E12: Yes | F12: 12 | G12: =IF(C12="","",IF(COUNTIF(B:B,B12)>1,"Duplicate Vendor",IF(AND(E12="Yes",D12>500),"High Recurring Cost",IF(D12>AVERAGE(D:D)*2.5,"Spending Spike","")))) | H12: =IF(C12="","",IF(E12="Yes",D12*F12,D12)) -> 2268 | J12: Links to other worksheets
A13: 46061 | B13: Protein Supplier | C13: Supplies | D13: 520 | E13: Yes | F13: 12 | G13: =IF(C13="","",IF(COUNTIF(B:B,B13)>1,"Duplicate Vendor",IF(AND(E13="Yes",D13>500),"High Recurring Cost",IF(D13>AVERAGE(D:D)*2.5,"Spending Spike","")))) -> High Recurring Cost | H13: =IF(C13="","",IF(E13="Yes",D13*F13,D13)) -> 6240 | J13: Links to other files
A14: 46063 | B14: Facebook Ads | C14: Marketing | D14: 380 | E14: Yes | F14: 12 | G14: =IF(C14="","",IF(COUNTIF(B:B,B14)>1,"Duplicate Vendor",IF(AND(E14="Yes",D14>500),"High Recurring Cost",IF(D14>AVERAGE(D:D)*2.5,"Spending Spike","")))) | H14: =IF(C14="","",IF(E14="Yes",D14*F14,D14)) -> 4560 | J14: Links to data providers (CIQ, FactSet)
A15: 46065 | B15: Electricity | C15: Utilities | D15: 310 | E15: Yes | F15: 12 | G15: =IF(C15="","",IF(COUNTIF(B:B,B15)>1,"Duplicate Vendor",IF(AND(E15="Yes",D15>500),"High Recurring Cost",IF(D15>AVERAGE(D:D)*2.5,"Spending Spike","")))) | H15: =IF(C15="","",IF(E15="Yes",D15*F15,D15)) -> 3720
A16: 46068 | B16: Equipment Lease | C16: Equipment | D16: 2200 | E16: Yes | F16: 12 | G16: =IF(C16="","",IF(COUNTIF(B:B,B16)>1,"Duplicate Vendor",IF(AND(E16="Yes",D16>500),"High Recurring Cost",IF(D16>AVERAGE(D:D)*2.5,"Spending Spike","")))) -> High Recurring Cost | H16: =IF(C16="","",IF(E16="Yes",D16*F16,D16)) -> 26400
A17: 46073 | B17: ClassPass Software | C17: Software | D17: 299 | E17: Yes | F17: 12 | G17: =IF(C17="","",IF(COUNTIF(B:B,B17)>1,"Duplicate Vendor",IF(AND(E17="Yes",D17>500),"High Recurring Cost",IF(D17>AVERAGE(D:D)*2.5,"Spending Spike","")))) -> Duplicate Vendor | H17: =IF(C17="","",IF(E17="Yes",D17*F17,D17)) -> 3588

Sheet AI Feed
A1: AI Analysis Feed
A2: (This tab formats model outputs for LLM strategic review. Copy A4:B40 and paste into the prompt.)
A4: Financial Model Summary | D4: Color Key — Cell Types
A5: Year 1 Revenue | B5: ='Income Statement'!N13 -> 393041.93 | D5: Hard-coded inputs
A6: Year 2 Revenue | B6: ='Income Statement'!O13 -> 531163.1 | D6: Formulas / calculations
A7: Year 3 Revenue | B7: ='Income Statement'!P13 -> 643256.05 | D7: Links to other worksheets
A8: Year 1 Net Income | B8: ='Income Statement'!N32 -> -103752.49 | D8: Links to other files
A9: Year 2 Net Income | B9: ='Income Statement'!O32 -> 15133.207 | D9: Links to data providers (CIQ, FactSet)
A10: Year 3 Net Income | B10: ='Income Statement'!P32 -> 95422.788
A11: Year 1 EBITDA | B11: ='Income Statement'!N26 -> -79952.489
A12: Year 3 EBITDA | B12: ='Income Statement'!P26 -> 144588.34
A13: Year 1 Ending Cash | B13: =Cash!C22 -> -26260.371
A16: Unit Economics
A17: Avg Member Lifespan (mo) | B17: ='Unit Economics'!B5 -> 25
A18: LTV (per member) | B18: ='Unit Economics'!B20 -> 1925
A19: CAC | B19: ='Unit Economics'!B17 -> 140
A20: LTV:CAC Ratio | B20: ='Unit Economics'!B21 -> 13.75
A21: CAC Payback (mo) | B21: ='Unit Economics'!B22 -> 1.8181818
A22: Gross Margin per Member | B22: ='Unit Economics'!B12 -> 0.86516854
A24: Expense Leakage Audit
A25: Total Annualized Spend | B25: ='Leakage Audit'!K3 -> 79126
A26: Items Flagged | B26: ='Leakage Audit'!K2 -> 6
A27: Flagged Annualized Cost | B27: ='Leakage Audit'!K4 -> 51216
A28: Potential Annual Savings | B28: ='Leakage Audit'!K5 -> 30729.6
A29: Leakage % of Spend | B29: ='Leakage Audit'!K6 -> 0.64727144
A31: Key Assumptions
A32: Starting Members | B32: =Assumptions!B4 -> 300
A33: Monthly New Members | B33: =Assumptions!B5 -> 25
A34: Monthly Churn Rate | B34: =Assumptions!B6 -> 0.04
A35: Avg Monthly Fee | B35: =Assumptions!B7 -> 89
A36: Monthly Fixed Costs | B36: =Assumptions!B11+Assumptions!B12+Assumptions!B13+Assumptions!B14+Assumptions!B15 -> 35000

Sheet Prompt Library (Ai Prompts)
A1: Prompt 1 - The CFO Strategic Brief
A2: You are a Strategic Finance Director writing a CFO-level brief for the owner of a boutique fitness studio. Below is a complete financial intelligence feed: a 3-year model summary, unit economics, and an expense leakage audit. Write a one-page executive brief with four sections: 1. FINANCIAL TRAJECTORY -> interpret the revenue and profitability path; identify the operating-leverage inflection and what drives it. 2. LIQUIDITY RISK -> assess the Year 1 cash position and funding need; state plainly whether the business needs outside capital and roughly how much. 3. UNIT ECONOMICS HEALTH -> evaluate the LTV:CAC ratio and payback; is customer acquisition efficient and sustainable? 4. TOP 3 RECOMMENDED ACTIONS -> specific, prioritized moves the owner should make. Be direct and quantitative. Cite the actual numbers. Write for a smart owner who is not a finance expert. [PASTE AI FEED DATA HERE]
A4: Prompt 2 - The Expense Auditor (Leakage Deep Dive)
A5: You are a Senior Auditor from a Big 4 firm reviewing flagged expenses for a small business. Below are transactions flagged by an automated anomaly-detection system, plus the audit summary. For each flagged item, assess whether it represents TRUE waste (duplicate tool, unused subscription, vendor overcharge) versus JUSTIFIED spend. Then provide: -> A prioritized list of expenses to cut or renegotiate, with annual dollar impact -> The single highest-confidence saving opportunity -> A realistic total recoverable figure (not 100% of flagged — some flags are false positives) Be skeptical and specific. [PASTE FLAGGED ITEMS + AUDIT SUMMARY HERE]
A7: Prompt 3 - The Scenario Translator (Plain English)
A8: You are a financial analyst explaining model scenarios to a non-finance business owner. Given the assumptions and outputs below, explain in plain language: - What happens to profitability and cash if monthly churn rises from its current rate to 8% - What happens if the membership fee increases by $10 - Which single variable has the largest impact on the bottom line, and why Use simple language and concrete dollar figures. No jargon. [PASTE KEY ASSUMPTIONS + OUTPUTS HERE]

Sheet Sample Output
B2: Prompt 1 Output — The CFO Strategic Brief
B4: 1. FINANCIAL TRAJECTORY
B5: The business is on a credible path from heavy startup losses to durable profitability. Revenue grows from $393K (Y1) to $531K (Y2) to $643K (Y3) — roughly 64% over three years, with the biggest jump (+35%) in Year 2. More importantly, net income swings from a $104K loss in Year 1 to +$15K in Year 2 to +$95K in Year 3.
B6: The operating-leverage inflection happens in Year 2, when you cross from loss to profit. The driver is structural: your fixed costs (~$35K/month, ~$420K/year) stay roughly flat while revenue climbs and each new member carries an 87% gross margin. Once revenue clears the fixed-cost hurdle, almost every additional dollar falls to the bottom line. That's why EBITDA nearly triples from -$80K (Y1) to +$145K (Y3) — you're spreading the same fixed base over a growing membership.
B8: 2. LIQUIDITY RISK
B9: This is the one genuine threat. Year 1 ending cash is -$26.3K — the model literally runs out of money before the business turns the corner. Profitability in Year 2 doesn't help you if you can't survive Year 1.
B10: Plainly: yes, you need outside capital. The math says you'd dip about $26K below zero, but you should never run a business to a razor-thin or negative balance. Raise a buffer that covers the trough plus operating margin for surprises — target $75K–$100K in working capital (line of credit, owner injection, or a small SBA loan). This bridges you through the Year 1 loss and the early-Year-2 ramp without a cash emergency.
B12: 3. UNIT ECONOMICS HEALTH
B13: Your unit economics are excellent — arguably the strongest part of the business.
B14: • LTV:CAC = 13.75 (LTV $1,925 vs. CAC $140). Healthy is 3:1; you're at nearly 14:1.
B15: • CAC payback = 1.8 months — you recoup acquisition cost in under two months.
B16: • Gross margin per member = 87%, over a 25-month average lifespan.
... B22: 3. Lean into acquisition once funded. With 13.75:1 LTV:CAC and 1.8-month payback, accelerating member growth above the current 25/month is the clearest lever to pull profitability forward — but only after the cash buffer is in place. Watch the 4% monthly churn closely; even a 1-point reduction meaningfully extends LTV and compounds everything above.
